aliddns_core/__init__.py
aliddns_core/ddns.py
aliddns_core/version.py
aliddns_core-1.0.7.dist-info/METADATA
aliddns_core-1.0.7.dist-info/WHEEL
aliddns_core-1.0.7.dist-info/top_level.txt
aliddns_core-1.0.7.dist-info/RECORD
